poketypes/__init__.py
poketypes/dex/__init__.py
poketypes/dex/dexdata.py
poketypes/dex/dexdata_pb2.py
poketypes/dex/dexdata_pb2.pyi
poketypes/dex/pokedex.py
poketypes/protos/__init__.py
poketypes/protos/basics.proto
poketypes/protos/dexdata.proto
poketypes/protos/mergers.py
poketypes/protos/protogen.py
poketypes/protos/statics.py
poketypes/showdown/__init__.py
poketypes/showdown/battlemessage.py
poketypes/showdown/showdownmessage.py
poketypes-0.2.6.dist-info/LICENSE
poketypes-0.2.6.dist-info/METADATA
poketypes-0.2.6.dist-info/WHEEL
poketypes-0.2.6.dist-info/RECORD
