Metadata-Version: 2.1
Name: poketypes
Version: 0.2.6
Summary: Automated classes with full typehinting support for pokemon, abilities, items, and so much more
Home-page: https://github.com/trevorWieland/poketypes
License: MIT
Author: Trevor Wieland
Author-email: trevor_wieland@mac.com
Requires-Python: >=3.9,<3.13
Classifier: License :: OSI Approved :: MIT License
Classifier: Programming Language :: Python :: 3
Classifier: Programming Language :: Python :: 3.9
Classifier: Programming Language :: Python :: 3.10
Classifier: Programming Language :: Python :: 3.11
Requires-Dist: protobuf (>=4.24.4,<5.0.0)
Requires-Dist: pydantic (>=2.4.2,<3.0.0)
Project-URL: Documentation, https://trevorwieland.github.io/poketypes/
Project-URL: Repository, https://github.com/trevorWieland/poketypes
